otupy/__init__.py
otupy/actuators/__init__.py
otupy/actuators/ctxd/__init__.py
otupy/actuators/ctxd/ctxd_actuator.py
otupy/actuators/ctxd/ctxd_actuator_docker.py
otupy/actuators/ctxd/ctxd_actuator_kubernetes.py
otupy/actuators/ctxd/ctxd_actuator_openstack.py
otupy/actuators/slpf/__init__.py
otupy/actuators/slpf/dumb_actuator.py
otupy/actuators/slpf/mockup_slpf_actuator.py
otupy/actuators/slpf/slpf_actuator.py
otupy/actuators/slpf/slpf_actuator_azure.py
otupy/actuators/slpf/slpf_actuator_iptables.py
otupy/actuators/slpf/slpf_actuator_kubernetes.py
otupy/actuators/slpf/slpf_actuator_openstack.py
otupy/actuators/slpf/sql_database.py
otupy/apps/__init__.py
otupy/apps/connector/__init__.py
otupy/apps/connector/connector.py
otupy/apps/connector/connector.yaml
otupy/apps/connector/config-templates/connector.yaml
otupy/apps/connector/config-templates/ctxd-kubernetes.yaml.template
otupy/apps/connector/config-templates/ctxd-openstack.yaml.template
otupy/apps/connector/config-templates/slpf-iptables.yaml.template
otupy/apps/connector/config-templates/slpf-kubernetes.yaml.template
otupy/apps/connector/config-templates/slpf-openstack.yaml.template
otupy/apps/ctxd/__init__.py
otupy/apps/ctxd/api_service.py
otupy/apps/ctxd/defaults.py
otupy/apps/ctxd/discover_functions.py
otupy/apps/ctxd/discovery.py
otupy/apps/ctxd/discovery.yaml.template
otupy/apps/ctxd/graphics.py
otupy/apps/ctxd/publishers.py
otupy/core/__init__.py
otupy/core/actions.py
otupy/core/actuator.py
otupy/core/args.py
otupy/core/command.py
otupy/core/consumer.py
otupy/core/content.py
otupy/core/content_type.py
otupy/core/encoder.py
otupy/core/extensions.py
otupy/core/message.py
otupy/core/producer.py
otupy/core/profile.py
otupy/core/register.py
otupy/core/response.py
otupy/core/results.py
otupy/core/target.py
otupy/core/transfer.py
otupy/core/version.py
otupy/encoders/__init__.py
otupy/encoders/cbor.py
otupy/encoders/json.py
otupy/encoders/xml.py
otupy/encoders/yaml.py
otupy/profiles/__init__.py
otupy-1.1.12.dist-info/METADATA
otupy-1.1.12.dist-info/WHEEL
otupy-1.1.12.dist-info/licenses/LICENSE.md
otupy-1.1.12.dist-info/RECORD
