Metadata-Version: 2.4
Name: otupy
Version: 1.1.12
Summary: OpenC2 Utilities for Python - Library and applications
Project-URL: Homepage, https://github.com/mattereppe/otupy/
Project-URL: Documentation, https://otupy.readthedocs.io
Project-URL: Issues, https://github.com/mattereppe/otupy/issues/
Author-email: Matteo Repetto <matteo.repetto@ge.imati.cnr.it>
License-File: LICENSE.md
Keywords: openc2
Classifier: Development Status :: 3 - Alpha
Classifier: Environment :: Console
Classifier: Intended Audience :: Developers
Classifier: License :: OSI Approved :: European Union Public Licence 1.2 (EUPL 1.2)
Classifier: Natural Language :: English
Classifier: Operating System :: OS Independent
Classifier: Programming Language :: Python :: 3.11
Classifier: Topic :: Security
Classifier: Topic :: Software Development :: Libraries
Classifier: Topic :: System :: Networking
Requires-Python: >=3.11
Requires-Dist: aenum>=3.1.15
Requires-Dist: apscheduler==3.11.2
Requires-Dist: azure-core==1.37.0
Requires-Dist: azure-identity==1.25.1
Requires-Dist: azure-mgmt-network==30.1.0
Requires-Dist: azure-mgmt-resource==24.0.0
Requires-Dist: cbor2==5.6.5
Requires-Dist: docker-py==1.10.6
Requires-Dist: email-validator>=2.2.0
Requires-Dist: flask>=3.1.0
Requires-Dist: fqdn>=1.5.1
Requires-Dist: idna>=3.10
Requires-Dist: kafka-python==2.3.0
Requires-Dist: kubernetes==34.1.0
Requires-Dist: macaddress>=2.0.2
Requires-Dist: mediatype>=0.1.6
Requires-Dist: openstacksdk==4.8.0
Requires-Dist: paho-mqtt==2.1.0
Requires-Dist: pymongo==4.15.5
Requires-Dist: requests>=2.31.0
Requires-Dist: requests>=2.32.3
Requires-Dist: rfc3987>=1.3.8
Requires-Dist: werkzeug>=3.0.2
Requires-Dist: xmltodict==0.14.2
